napari_aideveloper/.DS_Store
napari_aideveloper/Empty.rtdc
napari_aideveloper/__init__.py
napari_aideveloper/_widget.py
napari_aideveloper/aid_bin.py
napari_aideveloper/aid_dl.py
napari_aideveloper/aid_frontend_func.py
napari_aideveloper/aid_img.py
napari_aideveloper/aid_settings.json
napari_aideveloper/aid_start.py
napari_aideveloper/get_function_name.py
napari_aideveloper/model_zoo.py
napari_aideveloper/napari.yaml
napari_aideveloper/UI/.DS_Store
napari_aideveloper/UI/.arch
napari_aideveloper/UI/MyWidget.py
napari_aideveloper/UI/PopupFitting.ui
napari_aideveloper/UI/art.qrc
napari_aideveloper/UI/art_rc.py
napari_aideveloper/UI/napari_AID.py
napari_aideveloper/UI/napari_AID.ui
napari_aideveloper/UI/icon/CPU.png
napari_aideveloper/UI/icon/Hue.png
napari_aideveloper/UI/icon/add.png
napari_aideveloper/UI/icon/average_blur.png
napari_aideveloper/UI/icon/brightness_add.png
napari_aideveloper/UI/icon/brightness_mul.png
napari_aideveloper/UI/icon/color.png
napari_aideveloper/UI/icon/continue.png
napari_aideveloper/UI/icon/contrast.png
napari_aideveloper/UI/icon/crop.png
napari_aideveloper/UI/icon/delete.png
napari_aideveloper/UI/icon/flip_h.png
napari_aideveloper/UI/icon/flip_v.png
napari_aideveloper/UI/icon/gauss.png
napari_aideveloper/UI/icon/gaussian_noise_mean.png
napari_aideveloper/UI/icon/gaussian_noise_scale.png
napari_aideveloper/UI/icon/icon.qrc
napari_aideveloper/UI/icon/load.png
napari_aideveloper/UI/icon/model_path.png
napari_aideveloper/UI/icon/motion.png
napari_aideveloper/UI/icon/multi.png
napari_aideveloper/UI/icon/new.png
napari_aideveloper/UI/icon/normalization.png
napari_aideveloper/UI/icon/nr_epochs.png
napari_aideveloper/UI/icon/padding.png
napari_aideveloper/UI/icon/padding_2.png
napari_aideveloper/UI/icon/pause.png
napari_aideveloper/UI/icon/pause.svg
napari_aideveloper/UI/icon/play.png
napari_aideveloper/UI/icon/restart.png
napari_aideveloper/UI/icon/rotate.png
napari_aideveloper/UI/icon/saturation.png
napari_aideveloper/UI/icon/save_epoch.png
napari_aideveloper-0.0.4.dist-info/LICENSE
napari_aideveloper-0.0.4.dist-info/METADATA
napari_aideveloper-0.0.4.dist-info/WHEEL
napari_aideveloper-0.0.4.dist-info/entry_points.txt
napari_aideveloper-0.0.4.dist-info/top_level.txt
napari_aideveloper-0.0.4.dist-info/RECORD
