Metadata-Version: 2.1
Name: napari-aideveloper
Version: 0.0.4
Summary: napari_aideveloper is a napari-plugin deived from AIDeveloper that allows you to train, evaluate and apply deep neural nets for image classification within a graphical user-interface (GUI).
Home-page: https://github.com/zcqwh/napari-aideveloper
Author: Chenqi Zhang
Author-email: cqzhang@g.ecc.u-tokyo.ac.jp
License: BSD-3-Clause
Project-URL: Bug Tracker, https://github.com/zcqwh/napari-aideveloper/issues
Project-URL: Documentation, https://github.com/zcqwh/napari-aideveloper#README.md
Project-URL: Source Code, https://github.com/zcqwh/napari-aideveloper
Project-URL: User Support, https://github.com/zcqwh/napari-aideveloper/issues
Classifier: Development Status :: 2 - Pre-Alpha
Classifier: Intended Audience :: Developers
Classifier: Framework :: napari
Classifier: Topic :: Software Development :: Testing
Classifier: Programming Language :: Python
Classifier: Programming Language :: Python :: 3
Classifier: Programming Language :: Python :: 3.8
Classifier: Programming Language :: Python :: 3.9
Classifier: Programming Language :: Python :: 3.10
Classifier: Operating System :: OS Independent
Classifier: License :: OSI Approved :: BSD License
Requires-Python: >=3.8
License-File: LICENSE
Requires-Dist: numpy
Requires-Dist: magicgui
Requires-Dist: qtpy
Requires-Dist: dclab (>=0.39.9)
Requires-Dist: h5py (>=3.6.0)
Requires-Dist: Keras-Applications (>=1.0.8)
Requires-Dist: keras (>=2.8.0)
Requires-Dist: keras-metrics (>=1.1.0)
Requires-Dist: napari-plugin-engine (>=0.2.0)
Requires-Dist: napari (>=0.4.14)
Requires-Dist: onnx (>=1.11.0)
Requires-Dist: opencv-contrib-python-headless (>=4.5.5.62)
Requires-Dist: openpyxl (>=3.0.9)
Requires-Dist: pandas (>=1.4.1)
Requires-Dist: Pillow (>=9.1.1)
Requires-Dist: psutil (>=5.9.0)
Requires-Dist: pyqtgraph (>=0.12.3)
Requires-Dist: pytest (>=7.1.2)
Requires-Dist: scikit-learn (>=1.1.1)
Requires-Dist: scipy (>=1.8.0)
Requires-Dist: setuptools (>=58.0.4)
Requires-Dist: six (>=1.16.0)
Requires-Dist: tensorboard (>=2.8.0)
Requires-Dist: tensorflow (>=2.8.0)
Requires-Dist: tf2onnx (>=1.9.3)
Requires-Dist: xlrd (>=2.0.1)
Provides-Extra: testing
Requires-Dist: tox ; extra == 'testing'
Requires-Dist: pytest ; extra == 'testing'
Requires-Dist: pytest-cov ; extra == 'testing'
Requires-Dist: pytest-qt ; extra == 'testing'
Requires-Dist: napari ; extra == 'testing'
Requires-Dist: pyqt5 ; extra == 'testing'
